koz/__init__.py
koz/analyzer.py
koz/cli.py
koz/config.py
koz/detector.py
koz/exporter.py
koz/git_integration.py
koz/parser.py
koz/py.typed
koz/schema.py
koz-0.1.1.dist-info/licenses/LICENSE
koz-0.1.1.dist-info/METADATA
koz-0.1.1.dist-info/WHEEL
koz-0.1.1.dist-info/entry_points.txt
koz-0.1.1.dist-info/top_level.txt
koz-0.1.1.dist-info/RECORD
